infosec/__init__.py
infosec/infosec.py
emptyvoid-0.1.0.dist-info/METADATA
emptyvoid-0.1.0.dist-info/WHEEL
emptyvoid-0.1.0.dist-info/top_level.txt
emptyvoid-0.1.0.dist-info/RECORD
