Metadata-Version: 2.1
Name: emptyvoid
Version: 0.1.0
Summary: A package to list docx and pkt files
Home-page: https://github.com/yourusername/infosec
Author: Your Name
Author-email: your.email@example.com
Classifier: Programming Language :: Python :: 3
Classifier: License :: OSI Approved :: MIT License
Classifier: Operating System :: OS Independent
Requires-Python: >=3.6
Requires-Dist: python-docx
